{"name":"_ws_source_meteo","range":{"col1":1,"row1":1,"col2":2,"row2":22},"rows":[["Variable","Value"],["external_temperature_c",9.95827],["wind_speed_unmuted_m_s",2.83825],["wind_speed_m_s",1.63522],["wind_direction_degrees",332],["wind_direction_compass",{"type":"hortimax.synopta.enum", "key":8787, "value":"NNW"}],["radiation_intensity_unmuted_w_m2",128.789],["radiation_intensity_w_m2",68.8511],["standard_radiation_intensity_w_m2",128.789],["radiation_sum_j_cm2",30.1055],["radiation_from_plant_w_m2",28],["precipitation",0],["relative_humidity_perc",81],["moisture_deficit_g_kg",1.4595],["moisture_deficit_g_m3",1.8159],["dew_point_temperature_c",6.85108],["abs_humidity_g_kg",6.13756],["enthalpy_kj_kg",25.4656],["enthalpy_kj_m3",31.6842],["atmospheric_pressure_hpa",1013],["status_meteo_station",{"type":"hortimax.synopta.enum", "key":8789, "value":"Actief"}],["status_meteo_station_communication",{"type":"hortimax.synopta.enum", "key":8796, "value":"Online"}]],"ts":"2021-05-14T08:24:21+02:00","pt":0}