{"name":"_ws_source_meteo","range":{"col1":1,"row1":1,"col2":2,"row2":22},"rows":[["Variable","Value"],["external_temperature_c",21.9354],["wind_speed_unmuted_m_s",4.38454],["wind_speed_m_s",2.51365],["wind_direction_degrees",114],["wind_direction_compass",{"type":"hortimax.synopta.enum", "key":8777, "value":"OZO"}],["radiation_intensity_unmuted_w_m2",949.715],["radiation_intensity_w_m2",581.115],["standard_radiation_intensity_w_m2",949.715],["radiation_sum_j_cm2",816.951],["radiation_from_plant_w_m2",94],["precipitation",0],["relative_humidity_perc",61],["moisture_deficit_g_kg",6.63045],["moisture_deficit_g_m3",7.88425],["dew_point_temperature_c",13.9845],["abs_humidity_g_kg",9.94576],["enthalpy_kj_kg",47.3152],["enthalpy_kj_m3",56.2624],["atmospheric_pressure_hpa",1013],["status_meteo_station",{"type":"hortimax.synopta.enum", "key":8789, "value":"Actief"}],["status_meteo_station_communication",{"type":"hortimax.synopta.enum", "key":8796, "value":"Online"}]],"ts":"2021-05-09T13:37:54+02:00","pt":0}