{"name":"_ws_source_meteo","range":{"col1":1,"row1":1,"col2":2,"row2":22},"rows":[["Variable","Value"],["external_temperature_c",17.2561],["wind_speed_unmuted_m_s",4.22177],["wind_speed_m_s",3.95227],["wind_direction_degrees",166],["wind_direction_compass",{"type":"hortimax.synopta.enum", "key":8779, "value":"ZZO"}],["radiation_intensity_unmuted_w_m2",563.763],["radiation_intensity_w_m2",470.133],["standard_radiation_intensity_w_m2",563.763],["radiation_sum_j_cm2",309.009],["radiation_from_plant_w_m2",98],["precipitation",0],["relative_humidity_perc",69],["moisture_deficit_g_kg",3.84991],["moisture_deficit_g_m3",4.66079],["dew_point_temperature_c",11.556],["abs_humidity_g_kg",8.46201],["enthalpy_kj_kg",38.769],["enthalpy_kj_m3",46.9346],["atmospheric_pressure_hpa",1013],["status_meteo_station",{"type":"hortimax.synopta.enum", "key":8789, "value":"Actief"}],["status_meteo_station_communication",{"type":"hortimax.synopta.enum", "key":8796, "value":"Online"}]],"ts":"2021-05-09T09:47:54+02:00","pt":0}